[
  {
    "title": "Pre-Performance Dinner for the Garde's Cinderella Ballet",
    "date": "2026-05-14",
    "displayDate": "Thursday, May 14, 2026",
    "time": "4:30 PM",
    "description": ""
  },
  {
    "title": "CT Storytellers Meeting",
    "date": "2026-05-14",
    "displayDate": "Thursday, May 14, 2026",
    "time": "9:30 AM",
    "description": ""
  },
  {
    "title": "Club Manager - Day Off",
    "date": "2026-05-16",
    "displayDate": "Saturday, May 16, 2026",
    "time": "12:00 AM",
    "description": ""
  },
  {
    "title": "Private Member Event",
    "date": "2026-05-19",
    "displayDate": "Tuesday, May 19, 2026",
    "time": "2:00 PM",
    "description": "Nancy Murray Book Club & Tea"
  },
  {
    "title": "CT Storytellers Meeting",
    "date": "2026-05-21",
    "displayDate": "Thursday, May 21, 2026",
    "time": "9:30 AM",
    "description": ""
  },
  {
    "title": "Club Manager Office Hours",
    "date": "2026-05-28",
    "displayDate": "Thursday, May 28, 2026",
    "time": "6:00 AM",
    "description": ""
  },
  {
    "title": "Annual Duckpin Bowling Banquet",
    "date": "2026-05-29",
    "displayDate": "Friday, May 29, 2026",
    "time": "5:30 PM",
    "description": ""
  },
  {
    "title": "First Friday",
    "date": "2026-06-05",
    "displayDate": "Friday, June 5, 2026",
    "time": "5:30 PM",
    "description": ""
  },
  {
    "title": "Church of the City Good Neighbors Project Work Day",
    "date": "2026-06-06",
    "displayDate": "Saturday, June 6, 2026",
    "time": "12:00 AM",
    "description": ""
  },
  {
    "title": "USA 250th Birthday Themed Trivia Game Night with BBQ",
    "date": "2026-06-12",
    "displayDate": "Friday, June 12, 2026",
    "time": "5:30 PM",
    "description": ""
  }
]